{"mean":{"confidence_interval":{"confidence_level":0.95,"lower_bound":19733855.659416664,"upper_bound":19768352.124301586},"point_estimate":19751429.11638492,"standard_error":8844.672935930415},"median":{"confidence_interval":{"confidence_level":0.95,"lower_bound":19721098.593333334,"upper_bound":19778148.12857143},"point_estimate":19760148.96875,"standard_error":14857.844569897698},"median_abs_dev":{"confidence_interval":{"confidence_level":0.95,"lower_bound":4659.372085194865,"upper_bound":48460.56808465406},"point_estimate":36302.94048449356,"standard_error":11682.990904345163},"slope":{"confidence_interval":{"confidence_level":0.95,"lower_bound":19731090.751798563,"upper_bound":19765559.98179012},"point_estimate":19748298.624415584,"standard_error":8821.58281239529},"std_dev":{"confidence_interval":{"confidence_level":0.95,"lower_bound":18219.512628045366,"upper_bound":35264.47023198315},"point_estimate":29459.505244143456,"standard_error":4361.800119815226}}