{"mean":{"confidence_interval":{"confidence_level":0.95,"lower_bound":45633649.49952381,"upper_bound":46605574.68523809},"point_estimate":46069832.438482136,"standard_error":250820.6051601487},"median":{"confidence_interval":{"confidence_level":0.95,"lower_bound":45520959.425,"upper_bound":46516277.25},"point_estimate":45694156.33333333,"standard_error":264709.38353263563},"median_abs_dev":{"confidence_interval":{"confidence_level":0.95,"lower_bound":72471.33996337652,"upper_bound":1238473.9500626922},"point_estimate":261810.60847693018,"standard_error":305839.83358383336},"slope":{"confidence_interval":{"confidence_level":0.95,"lower_bound":45531431.04048843,"upper_bound":47181805.25100497},"point_estimate":46320176.46298701,"standard_error":441033.0572194538},"std_dev":{"confidence_interval":{"confidence_level":0.95,"lower_bound":157162.7573749906,"upper_bound":1122381.4767658936},"point_estimate":835124.1363266299,"standard_error":233360.70161342155}}